LICENSE
robot_gait_vis/__init__.py
robot_gait_vis/gait_gen.py
robot_gait_vis/gaits.py
robot_gait_vis/leg.py
robot_gait_vis/planar_leg.py
robot_gait_vis/robot.py
robot_gait_vis/sideways_planar_leg.py
robot_gait_vis/simulate.py
robot_gait_vis/three_dof_leg.py
robot_gait_vis-0.1.2.dist-info/LICENSE
robot_gait_vis-0.1.2.dist-info/METADATA
robot_gait_vis-0.1.2.dist-info/WHEEL
robot_gait_vis-0.1.2.dist-info/RECORD
