Metadata-Version: 2.1
Name: robot-gait-vis
Version: 0.1.2
Summary: Simulate and visualize different walking robot configurations and gaits.
Home-page: https://github.com/zsilberstein/robot-gait-vis
License: MIT
Keywords: robotics,gait,visualize
Author: Zach Silberstein
Author-email: zach.silberstein@gmail.com
Requires-Python: >=3.9,<4.0
Classifier: Intended Audience :: Education
Classifier: License :: OSI Approved :: MIT License
Classifier: Programming Language :: Python :: 3
Classifier: Programming Language :: Python :: 3.9
Classifier: Programming Language :: Python :: 3.10
Classifier: Programming Language :: Python :: 3.11
Classifier: Programming Language :: Python :: 3.12
Classifier: Topic :: Scientific/Engineering :: Visualization
Requires-Dist: matplotlib (>=3.8.3,<4.0.0)
Requires-Dist: numpy (>=1.26.4,<2.0.0)
Project-URL: Repository, https://github.com/zsilberstein/robot-gait-vis
